testwill3838/example.py
testwill3838/init.py
testwill3838-1.0.0.dist-info/LICENSE
testwill3838-1.0.0.dist-info/WHEEL
testwill3838-1.0.0.dist-info/METADATA
testwill3838-1.0.0.dist-info/RECORD
